chame/__init__.py
chame/io/__init__.py
chame/pl/__init__.py
chame/pp/__init__.py
chame/tl/__init__.py
chame/util/__init__.py
chame/util/seq.py
chame-0.0.1.dev0.dist-info/LICENSE
chame-0.0.1.dev0.dist-info/WHEEL
chame-0.0.1.dev0.dist-info/METADATA
chame-0.0.1.dev0.dist-info/RECORD
