Metadata-Version: 2.1
Name: chame
Version: 0.0.1.dev0
Summary: Chromatin accessibility module
Author: Danila Bredikhin, Max Frank
Maintainer-email: Danila Bredikhin <danila.bredikhin@embl.de>
Requires-Python: >=3.8
Requires-Dist: anndata
Requires-Dist: mudata
Requires-Dist: scanpy
Requires-Dist: pybedtools
Requires-Dist: pysam
Requires-Dist: sphinx ; extra == "doc"
Requires-Dist: myst-parser ; extra == "doc"
Requires-Dist: sphinx-book-theme ; extra == "doc"
Requires-Dist: readthedocs-sphinx-search ; extra == "doc"
Requires-Dist: nbsphinx ; extra == "doc"
Requires-Dist: sphinx-automodapi ; extra == "doc"
Requires-Dist: sphinxcontrib-bibtex ; extra == "doc"
Requires-Dist: sphinx-autodoc-typehints ; extra == "doc"
Requires-Dist: pytest ; extra == "test"
Requires-Dist: pytest-cov ; extra == "test"
Project-URL: Documentation, https://gtca.github.io/chame
Project-URL: Home-page, https://github.com/gtca/chame
Project-URL: Source, https://github.com/gtca/chame
Provides-Extra: dev
Provides-Extra: doc
Provides-Extra: test
